humaan/__init__.py
humaan/main.py
humaan-0.0.0a1.dist-info/LICENSE
humaan-0.0.0a1.dist-info/METADATA
humaan-0.0.0a1.dist-info/WHEEL
humaan-0.0.0a1.dist-info/top_level.txt
humaan-0.0.0a1.dist-info/RECORD
