Metadata-Version: 2.1
Name: humaan
Version: 0.0.0a1
Summary: Humaan Python API library
Author-email: Humaan <support@humaan.ai>
License: Apache License
Project-URL: Homepage, https://github.com/humaan-ai/humaan-python
Project-URL: Repository, https://github.com/humaan-ai/humaan-python
License-File: LICENSE
